auto_update_ip.py
ez_ip_updater-2.0.0.dist-info/licenses/LICENSE
ez_ip_updater-2.0.0.dist-info/METADATA
ez_ip_updater-2.0.0.dist-info/WHEEL
ez_ip_updater-2.0.0.dist-info/entry_points.txt
ez_ip_updater-2.0.0.dist-info/top_level.txt
ez_ip_updater-2.0.0.dist-info/RECORD
