Metadata-Version: 2.4
Name: ez-ip-updater
Version: 2.0.0
Summary: Tự động phát hiện IP công cộng và cập nhật vào Google Cloud / AWS
Author: Le Quyet Tien
License: MIT License
Keywords: gcp,aws,ip,firewall,security-groups
Classifier: Programming Language :: Python :: 3
Classifier: License :: OSI Approved :: MIT License
Classifier: Operating System :: OS Independent
Requires-Python: >=3.7
License-File: LICENSE
Requires-Dist: requests
Provides-Extra: gcp
Requires-Dist: google-cloud-compute; extra == "gcp"
Requires-Dist: google-api-python-client; extra == "gcp"
Provides-Extra: aws
Requires-Dist: boto3; extra == "aws"
Provides-Extra: all
Requires-Dist: google-cloud-compute; extra == "all"
Requires-Dist: google-api-python-client; extra == "all"
Requires-Dist: boto3; extra == "all"
Dynamic: license-file
